stargazer_utils/__init__.py
stargazer_utils/context.py
stargazer_utils/decorators.py
stargazer_utils/files/__init__.py
stargazer_utils/files/json.py
stargazer_utils/iter.py
stargazer_utils/logging.py
stargazer_utils/mixins.py
stargazer_utils/py.typed
stargazer_utils/timer.py
stargazer_utils-1.1.0.dist-info/METADATA
stargazer_utils-1.1.0.dist-info/WHEEL
stargazer_utils-1.1.0.dist-info/RECORD
