Metadata-Version: 2.3
Name: stargazer-utils
Version: 1.1.0
Summary: Tools to help people shoot for the stars
Author: Robert Ferguson
Author-email: rmferguson@protonmail.com
Requires-Python: >=3.11
Classifier: Programming Language :: Python :: 3
Classifier: Programming Language :: Python :: 3.11
Classifier: Programming Language :: Python :: 3.12
Classifier: Programming Language :: Python :: 3.13
Project-URL: Homepage, https://github.com/rmferguson/stargazers
Project-URL: Repository, https://github.com/rmferguson/stargazers
